LICENSE
MANIFEST.in
README.md
setup.py
benchmarks/__init__.py
benchmarks/test_compiler.py
benchmarks/test_core.py
moa/__init__.py
moa/analysis.py
moa/array.py
moa/ast.py
moa/compiler.py
moa/dnf.py
moa/exception.py
moa/onf.py
moa/shape.py
moa/testing.py
moa/visualize.py
moa/backend/__init__.py
moa/backend/python.py
moa/frontend/__init__.py
moa/frontend/__main__.py
moa/frontend/array.py
moa/frontend/moa.py
moa/frontend/numpy.py
python_moa.egg-info/PKG-INFO
python_moa.egg-info/SOURCES.txt
python_moa.egg-info/dependency_links.txt
python_moa.egg-info/requires.txt
python_moa.egg-info/top_level.txt
tests/__init__.py
tests/conftest.py
tests/test_analysis.py
tests/test_array.py
tests/test_ast.py
tests/test_compiler.py
tests/test_dnf.py
tests/test_integration.py
tests/test_shape.py
tests/test_visualize.py
tests/backend/test_python.py
tests/frontend/test_array.py
tests/frontend/test_moa.py