Metadata-Version: 2.1
Name: python-moa
Version: 0.5.1
Summary: Python Mathematics of Arrays (MOA)
Home-page: https://github.com/Quansight-Labs/python-moa
Maintainer: Christopher Ostrouchov
Maintainer-email: costrouchov@quansight.com
License: BSD 3-Clause License (Revised)
Project-URL: Bug Reports, https://github.com/Quansight-Labs/python-moa/issues
Project-URL: Source, https://github.com/Quansight-Labs/python-moa/sampleproject/
Project-URL: Documentation, https://python-moa.readthedocs.io
Keywords: tensor,compiler,moa
Platform: UNKNOWN
Classifier: Development Status :: 3 - Alpha
Classifier: License :: OSI Approved :: BSD License
Classifier: Programming Language :: Python :: 3
Classifier: Programming Language :: Python :: 3.6
Classifier: Programming Language :: Python :: 3.7
Classifier: Programming Language :: Python :: 3 :: Only
Classifier: Intended Audience :: Developers
Classifier: Intended Audience :: Science/Research
Requires-Python: >=3.6
Provides-Extra: moa
Provides-Extra: viz
Provides-Extra: test
Provides-Extra: benchmark
Provides-Extra: docs
